FM12_transform/__init__.py
FM12_transform/bufr2geojson.py
FM12_transform/cli.py
FM12_transform/data2bufr.py
FM12_transform/elastic.py
FM12_transform/opensearch.py
FM12_transform/resources/__init__.py
FM12_transform/resources/station_list.csv
FM12_transform/resources/synop-mappings-307080.json
FM12_transform/resources/synop-mappings-307096.json
FM12_transform-0.0.27.dist-info/METADATA
FM12_transform-0.0.27.dist-info/WHEEL
FM12_transform-0.0.27.dist-info/entry_points.txt
FM12_transform-0.0.27.dist-info/top_level.txt
FM12_transform-0.0.27.dist-info/RECORD
