Metadata-Version: 2.1
Name: FM12_transform
Version: 0.0.27
Summary: Package for converting FM12 SYNOP TAC messages or an individual SYNOP message to BUFR4
Author-email: Alexander Thompson <alexander.thompson@noaa.gov>
Project-URL: Homepage, https://github.com/pypa/sampleproject
Project-URL: Bug Tracker, https://github.com/pypa/sampleproject/issues
Keywords: WMO,SYNOP,FM-12,BUFR,decoding,weather,observations
Classifier: Development Status :: 1 - Planning
Requires-Python: >=3.7
Requires-Dist: attrs ==22.2.0
Requires-Dist: click
Requires-Dist: numpy
Requires-Dist: csv2bufr
Requires-Dist: eccodes
Requires-Dist: cfunits
Requires-Dist: pymetdecoder
Requires-Dist: opensearch-py
